{
    "uniequip_002_rfalcn": [
        [
            {
                "name": "习惯使然",
                "CN": "在【沙洲遗闻】中，技能开启时，将自身携带的资源送至背包",
                "mod": "在【沙洲遗闻】中，自身技力自然回复速度+0.2/秒；技能开启时，将自身携带的资源送至背包",
                "upgradeDescription": ""
            }
        ],
        [
            {
                "name": "习惯使然",
                "CN": "在【沙洲遗闻】中，技能开启时，将自身携带的资源送至背包",
                "mod": "在【沙洲遗闻】中，自身技力自然回复速度+0.3/秒；技能开启时，将自身携带的资源送至背包",
                "upgradeDescription": ""
            }
        ]
    ]
}